cognee_mcp/__init__.py
cognee_mcp/server.py
mseep_cognee_mcp-0.1.2.dist-info/METADATA
mseep_cognee_mcp-0.1.2.dist-info/WHEEL
mseep_cognee_mcp-0.1.2.dist-info/entry_points.txt
mseep_cognee_mcp-0.1.2.dist-info/top_level.txt
mseep_cognee_mcp-0.1.2.dist-info/RECORD
