Metadata-Version: 2.4
Name: mseep-cognee-mcp
Version: 0.1.2
Summary: A MCP server project
Author-email: mseep <support@skydeck.ai>
Requires-Python: >=3.11
Requires-Dist: mcp>=1.1.1
Requires-Dist: openai==1.52.0
Requires-Dist: pydantic==2.8.2
Requires-Dist: python-dotenv==1.0.1
Requires-Dist: fastapi<0.110.0,>=0.109.2
Requires-Dist: uvicorn==0.22.0
Requires-Dist: requests==2.32.3
Requires-Dist: aiohttp==3.10.10
Requires-Dist: typing_extensions==4.12.2
Requires-Dist: nest_asyncio==1.6.0
Requires-Dist: numpy==1.26.4
Requires-Dist: datasets==3.1.0
Requires-Dist: falkordb==1.0.9
Requires-Dist: boto3<2.0.0,>=1.26.125
Requires-Dist: botocore<2.0.0,>=1.35.54
Requires-Dist: gunicorn<21.0.0,>=20.1.0
Requires-Dist: sqlalchemy==2.0.35
Requires-Dist: instructor==1.5.2
Requires-Dist: networkx<4.0.0,>=3.2.1
Requires-Dist: aiosqlite<0.21.0,>=0.20.0
Requires-Dist: pandas==2.0.3
Requires-Dist: filetype<2.0.0,>=1.2.0
Requires-Dist: nltk<4.0.0,>=3.8.1
Requires-Dist: dlt[sqlalchemy]<2.0.0,>=1.4.1
Requires-Dist: aiofiles<24.0.0,>=23.2.1
Requires-Dist: qdrant-client<2.0.0,>=1.9.0
Requires-Dist: graphistry<0.34.0,>=0.33.5
Requires-Dist: tenacity<9.0.0,>=8.4.1
Requires-Dist: weaviate-client==4.6.7
Requires-Dist: scikit-learn<2.0.0,>=1.5.0
Requires-Dist: pypdf<5.0.0,>=4.1.0
Requires-Dist: neo4j<6.0.0,>=5.20.0
Requires-Dist: jinja2<4.0.0,>=3.1.3
Requires-Dist: matplotlib<4.0.0,>=3.8.3
Requires-Dist: tiktoken==0.7.0
Requires-Dist: langchain_text_splitters==0.3.2
Requires-Dist: langsmith==0.1.139
Requires-Dist: langdetect==1.0.9
Requires-Dist: posthog<4.0.0,>=3.5.0
Requires-Dist: lancedb==0.15.0
Requires-Dist: litellm==1.49.1
Requires-Dist: groq==0.8.0
Requires-Dist: langfuse<3.0.0,>=2.32.0
Requires-Dist: pydantic-settings<3.0.0,>=2.2.1
Requires-Dist: anthropic<1.0.0,>=0.26.1
Requires-Dist: sentry-sdk[fastapi]<3.0.0,>=2.9.0
Requires-Dist: fastapi-users[sqlalchemy]
Requires-Dist: alembic<2.0.0,>=1.13.3
Requires-Dist: asyncpg==0.30.0
Requires-Dist: pgvector<0.4.0,>=0.3.5
Requires-Dist: psycopg2<3.0.0,>=2.9.10
Requires-Dist: llama-index-core<0.12.0,>=0.11.22
Requires-Dist: deepeval<3.0.0,>=2.0.1
Requires-Dist: transformers<5.0.0,>=4.46.3
Requires-Dist: pymilvus<3.0.0,>=2.5.0
Requires-Dist: unstructured[csv,doc,docx,epub,md,odt,org,ppt,pptx,rst,rtf,tsv,xlsx]<1.0.0,>=0.16.10
Requires-Dist: pytest<8.0.0,>=7.4.0
Requires-Dist: pytest-asyncio<0.22.0,>=0.21.1
Requires-Dist: coverage<8.0.0,>=7.3.2
Requires-Dist: mypy<2.0.0,>=1.7.1
Requires-Dist: deptry<0.21.0,>=0.20.0
Requires-Dist: debugpy==1.8.2
Requires-Dist: pylint<4.0.0,>=3.0.3
Requires-Dist: ruff<0.3.0,>=0.2.2
Requires-Dist: tweepy==4.14.0
Requires-Dist: gitpython<4.0.0,>=3.1.43
Requires-Dist: cognee
